MANIFEST.in
README.txt
setup.cfg
setup.py
authtkt/__init__.py
authtkt/auth_tkt.py
authtkt/middleware.py
authtkt/models.py
authtkt/urls.py
authtkt/views.py
authtkt/templates/authtkt/base.html
authtkt/templates/authtkt/index.html
authtkt/tests/__init__.py
authtkt/tests/functionnal.py
authtkt/tests/test_index.py
django_authtkt.egg-info/PKG-INFO
django_authtkt.egg-info/SOURCES.txt
django_authtkt.egg-info/dependency_links.txt
django_authtkt.egg-info/entry_points.txt
django_authtkt.egg-info/not-zip-safe
django_authtkt.egg-info/requires.txt
django_authtkt.egg-info/top_level.txt