Metadata-Version: 1.0
Name: django-authtkt
Version: 0.3
Summary: django-authtkt is used to share auth between more than one django site (a kind of SSO auth)
Home-page: https://github.com/bearstech/django-authtkt
Author: Bearstech
Author-email: py@beasrtech.com
License: GPL
Keywords: django auth cookie
Platform: UNKNOWN
Classifier: Framework :: Django
Classifier: Intended Audience :: Developers
